rentry/__init__.py
rentry/cli.py
rentry/client.py
rentry/data.py
rentry/errors.py
rentry/metadata.py
rentry_py-0.3.9.dist-info/METADATA
rentry_py-0.3.9.dist-info/WHEEL
rentry_py-0.3.9.dist-info/entry_points.txt
rentry_py-0.3.9.dist-info/licenses/LICENSE
rentry_py-0.3.9.dist-info/RECORD
