Metadata-Version: 2.4
Name: rentry.py
Version: 0.3.9
Summary: A python wrapper for the rentry markdown service.
Project-URL: Homepage, https://pypi.org/project/rentry.py/
Project-URL: Repository, https://github.com/EtorixDev/rentry.py/
Project-URL: Sponsor, https://github.com/sponsors/EtorixDev
Project-URL: Donate, https://ko-fi.com/Etorix
Author-email: Etorix <admin@etorix.dev>
License-Expression: MIT
License-File: LICENSE
Keywords: api,asynchronous,command line,markdown,rentry,synchronous,wrapper
Classifier: License :: OSI Approved :: MIT License
Classifier: Programming Language :: Python :: 3
Classifier: Programming Language :: Python :: 3.9
Classifier: Programming Language :: Python :: 3.10
Classifier: Programming Language :: Python :: 3.11
Classifier: Programming Language :: Python :: 3.12
Classifier: Programming Language :: Python :: 3.13
Classifier: Programming Language :: Python :: 3.14
Requires-Python: >=3.9
Requires-Dist: httpx>=0.28.1
